README.txt
setup.cfg
setup.py
Products/__init__.py
Products.pluggablecatalog.egg-info/PKG-INFO
Products.pluggablecatalog.egg-info/SOURCES.txt
Products.pluggablecatalog.egg-info/dependency_links.txt
Products.pluggablecatalog.egg-info/entry_points.txt
Products.pluggablecatalog.egg-info/namespace_packages.txt
Products.pluggablecatalog.egg-info/not-zip-safe
Products.pluggablecatalog.egg-info/requires.txt
Products.pluggablecatalog.egg-info/top_level.txt
Products/pluggablecatalog/README.txt
Products/pluggablecatalog/__init__.py
Products/pluggablecatalog/config.py
Products/pluggablecatalog/configure.zcml
Products/pluggablecatalog/interfaces.py
Products/pluggablecatalog/setuphandlers.py
Products/pluggablecatalog/tool.gif
Products/pluggablecatalog/tool.py
Products/pluggablecatalog/profiles/default/pluggablecatalog-default.txt
Products/pluggablecatalog/tests/__init__.py
Products/pluggablecatalog/tests/common.py
Products/pluggablecatalog/tests/testDoctests.py
Products/pluggablecatalog/tests/testSetup.py
docs/HISTORY.txt
docs/LICENSE.txt