Metadata-Version: 1.0
Name: Products.pluggablecatalog
Version: 1.0
Summary: pluggablecatalog is a replacement (or rather: a wrapper) for Plone's portal catalog
Home-page: http://svn.plone.org/svn/plone/plone.example
Author: Daniel Nouri
Author-email: plone-developers@lists.sourceforge.net
License: GPL
Download-URL: http://plone.org/products/pluggablecatalog
Platform: UNKNOWN
Classifier: Framework :: Plone
Classifier: Framework :: Zope2
Classifier: Programming Language :: Python
